[{"name": "Bruce Firmware", "author": "pr3y", "description": "VISIT https://bruce.computer\nCHECK OUR GITHUB! supporting CC1101 and NRF24\nhttps://github.com/pr3y/Bruce/\nWiFi - BLE - RFID - RF - GPS - FM - NRF24 - Connect - Others\n### Our wiki: https://github.com/pr3y/bruce/wiki ### Discord: https://discord.gg/WJ9XF9czVT", "cover": "41d9e573f8b7aca442af27f54d788a94.png", "versions": [{"version": "AVOK Mini v2", "published_at": "", "file": "https://github.com/pr3y/Bruce/releases/download/lastRelease/Bruce-Awok-Mini.bin", "Fs": 3251280, "s": false, "as": 3185744, "ss": 11993088, "so": 4718592}, {"version": "AWOK Touch v2", "published_at": "", "file": "https://github.com/pr3y/Bruce/releases/download/lastRelease/Bruce-Awok-Touch.bin", "Fs": 3254240, "s": false, "as": 3188704, "ss": 11993088, "so": 4718592}, {"version": "GUITON", "published_at": "", "file": "https://github.com/pr3y/Bruce/releases/download/lastRelease/Bruce-LAUNCHER_Phantom_S024R.bin", "Fs": 2618464, "s": false, "as": 2552928, "ss": 1572864, "so": 2621440}, {"version": "CYD S028R", "published_at": "", "file": "https://github.com/pr3y/Bruce/releases/download/lastRelease/Bruce-LAUNCHER_CYD-2432S028.bin", "Fs": 2619280, "s": false, "as": 2553744, "ss": 1572864, "so": 2621440}, {"version": "Mini", "published_at": "", "file": "https://github.com/pr3y/Bruce/releases/download/lastRelease/Bruce-LAUNCHER_Marauder-Mini.bin", "Fs": 2609920, "s": false, "as": 2544384, "ss": 1572864, "so": 2621440}, {"version": "V4 or V6", "published_at": "", "file": "https://github.com/pr3y/Bruce/releases/download/lastRelease/Bruce-LAUNCHER_Marauder-V4-V6.bin", "Fs": 2613296, "s": false, "as": 2547760, "ss": 1572864, "so": 2621440}, {"version": "V6.x", "published_at": "", "file": "https://github.com/pr3y/Bruce/releases/download/lastRelease/Bruce-LAUNCHER_Marauder-v61.bin", "Fs": 2613264, "s": false, "as": 2547728, "ss": 1572864, "so": 2621440}, {"version": "v7", "published_at": "", "file": "https://github.com/pr3y/Bruce/releases/download/lastRelease/Bruce-LAUNCHER_Marauder-v7.bin", "Fs": 2610144, "s": false, "as": 2544608, "ss": 1572864, "so": 2621440}], "fid": "CFWL4MORVG92RNJHNNOL2WO228TM5BZL", "category": "marauder"}, {"name": "Bruce Firmware (Beta)", "author": "pr3y", "description": "Bruce is a custom firmware for the M5Stack Carduputer, designed to enhance its functionality and user experience. This beta version includes new features and improvements over the stock firmware.", "cover": "41d9e573f8b7aca442af27f54d788a94.png", "versions": [{"version": "AVOK Mini v2", "published_at": "", "file": "https://github.com/pr3y/Bruce/releases/download/betaRelease/Bruce-Awok-Mini.bin", "Fs": 3675744, "s": false, "as": 3610208, "ss": 11993088, "so": 4718592}, {"version": "AWOK Touch v2", "published_at": "", "file": "https://github.com/pr3y/Bruce/releases/download/betaRelease/Bruce-Awok-Touch.bin", "Fs": 3679952, "s": false, "as": 3614416, "ss": 11993088, "so": 4718592}, {"version": "GUITON", "published_at": "", "file": "https://github.com/pr3y/Bruce/releases/download/betaRelease/Bruce-LAUNCHER_Phantom_S024R.bin", "Fs": 2614880, "s": false, "as": 2549344, "ss": 1572864, "so": 2621440}, {"version": "CYD S028R", "published_at": "", "file": "https://github.com/pr3y/Bruce/releases/download/betaRelease/Bruce-LAUNCHER_CYD-2432S028.bin", "Fs": 2615808, "s": false, "as": 2550272, "ss": 1572864, "so": 2621440}, {"version": "Mini", "published_at": "", "file": "https://github.com/pr3y/Bruce/releases/download/betaRelease/Bruce-LAUNCHER_Marauder-Mini.bin", "Fs": 2606768, "s": false, "as": 2541232, "ss": 1572864, "so": 2621440}, {"version": "V4 or V6", "published_at": "", "file": "https://github.com/pr3y/Bruce/releases/download/betaRelease/Bruce-LAUNCHER_Marauder-V4-V6.bin", "Fs": 2609952, "s": false, "as": 2544416, "ss": 1572864, "so": 2621440}, {"version": "V6.x", "published_at": "", "file": "https://github.com/pr3y/Bruce/releases/download/betaRelease/Bruce-LAUNCHER_Marauder-v61.bin", "Fs": 2609920, "s": false, "as": 2544384, "ss": 1572864, "so": 2621440}, {"version": "v7", "published_at": "", "file": "https://github.com/pr3y/Bruce/releases/download/betaRelease/Bruce-LAUNCHER_Marauder-v7.bin", "Fs": 2607024, "s": false, "as": 2541488, "ss": 1572864, "so": 2621440}, {"version": "WaveSentry", "published_at": "", "file": "https://github.com/pr3y/Bruce/releases/download/betaRelease/Bruce-LAUNCHER_WaveSentry-R1.bin", "Fs": 2610672, "s": false, "as": 2545136, "ss": 1572864, "so": 2621440}], "fid": "CFWXCBUI9VIIC4DAAF7I87IZVMSHFBC2", "category": "marauder"}, {"name": "Ghost v1.8.1", "author": "jaylikesbunda", "description": "Welcome to Ghost ESP, a robust and feature-rich firmware designed for your ESP32 microcontroller, enabling advanced wireless network exploration and security testing. With Ghost ESP installed, you can leverage the power of your ESP32 device to conduct in-depth WiFi and Bluetooth Low Energy (BLE) analysis, launch strategic wireless attacks, and explore a wide range of wireless environments.", "cover": "73a76385ad90e1e7537e066187476e77.png", "fid": "CFW65JYEX4CBVRVGK0CR8TIE9A4INIIX", "versions": [{"version": "AwokMini", "published_at": "03/11/25", "file": "https://github.com/bmorcelli/M5Stack-json-fw/releases/download/GhostESP/AwokMini.bin", "Fs": 1625888, "s": false, "as": 1625888, "nb": true}, {"version": "Crowtech_LCD", "published_at": "03/11/25", "file": "https://github.com/bmorcelli/M5Stack-json-fw/releases/download/GhostESP/Crowtech_LCD.bin", "Fs": 1908704, "s": false, "as": 1908704, "nb": true}, {"version": "CYD2USB", "published_at": "03/11/25", "file": "https://github.com/bmorcelli/M5Stack-json-fw/releases/download/GhostESP/CYD2USB.bin", "Fs": 2089216, "s": false, "as": 2089216, "nb": true}, {"version": "CYD2USB2.4Inch", "published_at": "03/11/25", "file": "https://github.com/bmorcelli/M5Stack-json-fw/releases/download/GhostESP/CYD2USB2.4Inch.bin", "Fs": 2089408, "s": false, "as": 2089408, "nb": true}, {"version": "CYD2USB2.4Inch_C", "published_at": "03/11/25", "file": "https://github.com/bmorcelli/M5Stack-json-fw/releases/download/GhostESP/CYD2USB2.4Inch_C.bin", "Fs": 2087344, "s": false, "as": 2087344, "nb": true}, {"version": "CYDDualUSB", "published_at": "03/11/25", "file": "https://github.com/bmorcelli/M5Stack-json-fw/releases/download/GhostESP/CYDDualUSB.bin", "Fs": 2078736, "s": false, "as": 2078736, "nb": true}, {"version": "CYDMicroUSB", "published_at": "03/11/25", "file": "https://github.com/bmorcelli/M5Stack-json-fw/releases/download/GhostESP/CYDMicroUSB.bin", "Fs": 2078768, "s": false, "as": 2078768, "nb": true}, {"version": "MarauderV6_AwokDual", "published_at": "03/11/25", "file": "https://github.com/bmorcelli/M5Stack-json-fw/releases/download/GhostESP/MarauderV6_AwokDual.bin", "Fs": 2012576, "s": false, "as": 2012576, "nb": true}], "category": "marauder"}, {"name": "Launcher", "author": "bmorcelli", "description": "With this app you can turn your device into a swiss knife, loading any .bin you have on your SD Card or wirelessly downloading from M5Burner repo or from your computer/smartphone through its WebUI. \nTutorial: https://youtu.be/odlHWZ03shI \nSupport me: https://buymeacoffee.com/bmorcelliz \nWiki: https://github.com/bmorcelli/Launcher/wiki/Obtaining-binaries-to-launch", "cover": "8a0100966905599183f9431ea873058f.gif", "versions": [{"version": "AVOK Mini v2", "published_at": "", "file": "https://github.com/bmorcelli/Launcher/releases/download/last/Launcher-Awok-Mini.bin", "Fs": 1467744, "s": false, "as": 1402208, "ss": 2949120, "so": 13631488}, {"version": "AWOK Touch v2", "published_at": "", "file": "https://github.com/bmorcelli/Launcher/releases/download/last/Launcher-Awok-Touch.bin", "Fs": 1471920, "s": false, "as": 1406384, "ss": 2949120, "so": 13631488}, {"version": "GUITON", "published_at": "", "file": "https://github.com/bmorcelli/Launcher/releases/download/last/Launcher-Phantom_S024R.bin", "Fs": 1472080, "s": false, "as": 1406544, "ss": 131072, "so": 4063232}, {"version": "CYD S028R", "published_at": "", "file": "https://github.com/bmorcelli/Launcher/releases/download/last/Launcher-CYD-2432S028.bin", "Fs": 1472032, "s": false, "as": 1406496, "ss": 131072, "so": 4063232}, {"version": "Mini", "published_at": "", "file": "https://github.com/bmorcelli/Launcher/releases/download/last/Launcher-Marauder-Mini.bin", "Fs": 1465616, "s": false, "as": 1400080, "ss": 131072, "so": 4063232}, {"version": "V4 or V6", "published_at": "", "file": "https://github.com/bmorcelli/Launcher/releases/download/last/Launcher-Marauder-v4-OG.bin", "Fs": 1469808, "s": false, "as": 1404272, "ss": 131072, "so": 4063232}, {"version": "V6.x", "published_at": "", "file": "https://github.com/bmorcelli/Launcher/releases/download/last/Launcher-Marauder-v61.bin", "Fs": 1469808, "s": false, "as": 1404272, "ss": 131072, "so": 4063232}, {"version": "v7", "published_at": "", "file": "https://github.com/bmorcelli/Launcher/releases/download/last/Launcher-Marauder-v7.bin", "Fs": 1466928, "s": false, "as": 1401392, "ss": 131072, "so": 4063232}], "fid": "CFW3XKD2YWFANIYBTPHSWV5KMF3VRS1B", "category": "marauder"}, {"name": "Marauder v1.9.0", "author": "JustCallMeKoko", "description": "A suite of WiFi/Bluetooth offensive and defensive tools for the ESP32. Use Launcher to install", "cover": "3183675bd52534e015bcc8ae2ae603a0.png", "fid": "CFWP2BWSUATAASEAEN3IAMKMVSL4WFS3", "versions": [{"version": "GUITON", "published_at": "13/12/25", "file": "https://github.com/justcallmekoko/ESP32Marauder/releases/download/v1.9.0/esp32_marauder_v1_9_0_20251213_cyd_2432S024_guition.bin", "Fs": 1521184, "s": false, "as": 1521184, "nb": true}, {"version": "CYD S028R", "published_at": "13/12/25", "file": "https://github.com/justcallmekoko/ESP32Marauder/releases/download/v1.9.0/esp32_marauder_v1_9_0_20251213_cyd_2432S028.bin", "Fs": 1523376, "s": false, "as": 1523376, "nb": true}, {"version": "CYD S028R", "published_at": "13/12/25", "file": "https://github.com/justcallmekoko/ESP32Marauder/releases/download/v1.9.0/esp32_marauder_v1_9_0_20251213_cyd_2432S028_2usb.bin", "Fs": 1523232, "s": false, "as": 1523232, "nb": true}, {"version": "V7", "published_at": "13/12/25", "file": "https://github.com/justcallmekoko/ESP32Marauder/releases/download/v1.9.0/esp32_marauder_v1_9_0_20251213_marauder_v7.bin", "Fs": 1541040, "s": false, "as": 1541040, "nb": true}, {"version": "V7.1", "published_at": "13/12/25", "file": "https://github.com/justcallmekoko/ESP32Marauder/releases/download/v1.9.0/esp32_marauder_v1_9_0_20251213_marauder_v7_1.bin", "Fs": 1560096, "s": false, "as": 1560096, "nb": true}, {"version": "Mini", "published_at": "13/12/25", "file": "https://github.com/justcallmekoko/ESP32Marauder/releases/download/v1.9.0/esp32_marauder_v1_9_0_20251213_mini.bin", "Fs": 1517920, "s": false, "as": 1517920, "nb": true}, {"version": "V4", "published_at": "13/12/25", "file": "https://github.com/justcallmekoko/ESP32Marauder/releases/download/v1.9.0/esp32_marauder_v1_9_0_20251213_old_hardware.bin", "Fs": 1544016, "s": false, "as": 1544016, "nb": true}, {"version": "V6", "published_at": "13/12/25", "file": "https://github.com/justcallmekoko/ESP32Marauder/releases/download/v1.9.0/esp32_marauder_v1_9_0_20251213_v6.bin", "Fs": 1545056, "s": false, "as": 1545056, "nb": true}, {"version": "v6.x", "published_at": "13/12/25", "file": "https://github.com/justcallmekoko/ESP32Marauder/releases/download/v1.9.0/esp32_marauder_v1_9_0_20251213_v6_1.bin", "Fs": 1545056, "s": false, "as": 1545056, "nb": true}], "category": "marauder"}, {"name": "WaveSentry Factory Firmware", "author": "OpenSourceSDRLabs", "description": "", "cover": "https://ueeshop.ly200-cdn.com/u_file/UPBD/UPBD268/2509/09/products/39713.jpg", "versions": [{"version": "1.0.0", "published_at": "2025-10-08", "file": "https://github.com/OpenSourceSDRLab/WaveSentry/releases/download/v1.0.0/wavesentry_pro.ino.bin", "Fs": 1399968, "s": false, "as": 1399968, "nb": true}], "fid": "CFWSVKGQVKXWM081B89CGSFNTCQTM3HB", "category": "marauder"}]