[{"name": "Bruce Firmware", "author": "pr3y", "versions": [{"version": "CC1101", "published_at": "", "file": "https://github.com/pr3y/Bruce/releases/download/lastRelease/Bruce-lilygo-t-embed-cc1101.bin", "Fs": 4039936, "s": false, "as": 3974400, "ss": 11993088, "so": 4718592}, {"version": "Non CC1101", "published_at": "", "file": "https://github.com/pr3y/Bruce/releases/download/lastRelease/Bruce-lilygo-t-embed.bin", "Fs": 4033552, "s": false, "as": 3968016, "ss": 11993088, "so": 4718592}], "category": "t-embed-cc1101"}, {"name": "Bruce Firmware (BETA)", "author": "pr3y", "versions": [{"version": "CC1101", "published_at": "", "file": "https://github.com/pr3y/Bruce/releases/download/betaRelease/Bruce-lilygo-t-embed-cc1101.bin", "Fs": 4039936, "s": false, "as": 3974400, "ss": 11993088, "so": 4718592}, {"version": "Non CC1101", "published_at": "", "file": "https://github.com/pr3y/Bruce/releases/download/betaRelease/Bruce-lilygo-t-embed.bin", "Fs": 4033552, "s": false, "as": 3968016, "ss": 11993088, "so": 4718592}], "category": "t-embed-cc1101"}, {"name": "Capibara Zero", "author": "Capibara", "versions": [{"version": "Lastest", "published_at": "", "file": "https://github.com/CapibaraZero/Web-Flasher/raw/refs/heads/main/public/firmware/lilygo_t_embed_cc1101/latest_beta/firmware.bin", "Fs": 1986464, "s": false, "as": 1986464, "nb": true}], "category": "t-embed-cc1101"}, {"name": "Capibara Zero (BETA)", "author": "Capibara", "versions": [{"version": "beta", "published_at": "", "file": "https://github.com/CapibaraZero/Web-Flasher/raw/refs/heads/main/public/firmware/lilygo_t_embed_cc1101/latest_stable/firmware.bin", "Fs": 1986464, "s": false, "as": 1986464, "nb": true}], "category": "t-embed-cc1101"}, {"name": "ESP32 Bus Pirate", "author": "geo-tp", "versions": [{"version": "v0.6 CC1101", "published_at": "", "file": "https://github.com/geo-tp/ESP32-Bus-Pirate/releases/download/v0.6/bus_pirate_06_tembeds3cc1101.bin", "Fs": 2904784, "s": false, "as": 2839248, "ss": 1572864, "so": 6750208}, {"version": "v0.6 regular", "published_at": "", "file": "https://github.com/geo-tp/ESP32-Bus-Pirate/releases/download/v0.6/bus_pirate_06_tembeds3.bin", "Fs": 2904832, "s": false, "as": 2839296, "ss": 1572864, "so": 6750208}], "category": "t-embed-cc1101"}, {"name": "Factory Firmware", "author": "Lilygo", "versions": [{"version": "CC1101", "published_at": "", "file": "https://github.com/Xinyuan-LilyGO/T-Embed-CC1101/raw/refs/heads/master/firmware/factory_v1.1_20250109.bin", "Fs": 0, "s": false, "as": 0, "nb": true}, {"version": "Non CC1101", "published_at": "", "file": "https://github.com/Xinyuan-LilyGO/T-Embed/raw/refs/heads/main/firmware/firmware.bin", "Fs": 2018512, "s": false, "as": 1952976, "ss": 917504, "so": 3211264}], "category": "t-embed-cc1101"}, {"name": "Ghost v1.7.2", "author": "jaylikesbunda", "versions": [{"version": "LilyGo-TEmbedC1101", "published_at": "06/09/25", "file": "https://github.com/bmorcelli/M5Stack-json-fw/releases/download/GhostESP/LilyGo-TEmbedC1101.bin", "Fs": 2145312, "s": false, "as": 2145312, "nb": true}], "category": "t-embed-cc1101"}, {"name": "Launcher", "author": "bmorcelli", "versions": [{"version": "CC1101", "published_at": "", "file": "https://github.com/bmorcelli/Launcher/releases/download/last/Launcher-lilygo-t-embed-cc1101.bin", "Fs": 1486800, "s": false, "as": 1421264, "ss": 2949120, "so": 13631488}, {"version": "Non CC1101", "published_at": "", "file": "https://github.com/bmorcelli/Launcher/releases/download/last/Launcher-lilygo-t-embed.bin", "Fs": 1480000, "s": false, "as": 1414464, "ss": 2949120, "so": 13631488}], "category": "t-embed-cc1101"}]